{
  "sections": {
    "main": {
      "type": "main-product",
      "blocks": {
        "title": {
          "type": "title",
          "settings": {
            "heading_tag": "h2"
          }
        },
        "e00585ce-7192-4586-9567-a2c4bafdd045": {
          "type": "price_smartrr",
          "settings": {
          }
        },
        "3780c535-8911-4fe4-8d1f-605124beb58c": {
          "type": "text",
          "settings": {
            "text": "<p>{{ product.metafields.my_fields.short_description | metafield_tag }}<\/p>"
          }
        },
        "8d21c681-30df-4742-8a3a-4317b834ba98": {
          "type": "text",
          "settings": {
            "text": "{{ product.metafields.custom.product_key_benefit | metafield_tag }}"
          }
        },
        "variant_picker": {
          "type": "variant_picker",
          "settings": {
            "hide_sold_out_variants": false,
            "stack_blocks": true,
            "selector_mode": "block",
            "color_mode": "color",
            "size_chart_page": ""
          }
        },
        "607f9e51-9129-4c62-b3f5-158106b03c22": {
          "type": "shopify:\/\/apps\/smartrr\/blocks\/app-block\/feefa72b-d730-4320-ae1b-95af6a0c861e",
          "settings": {
            "group_select": "pills",
            "group_border": 1,
            "group_border_radius": 10,
            "group_primary_background": "#ffffff",
            "group_primary_text_color": "#1a1a1a",
            "group_border_color": "#e93b40",
            "show_otp": true,
            "otp_default": true,
            "show_prices": true,
            "plan_select": "pills",
            "plan_border": 1,
            "plan_border_radius": 8,
            "show_label": false,
            "plan_primary_background": "#ffffff",
            "plan_primary_text_color": "#202223",
            "plan_border_color": "#202223",
            "custom_css": ""
          }
        },
        "3cbe7afa-04db-4038-8417-654d1167e569": {
          "type": "buy_buttons_quantite",
          "settings": {
            "show_payment_button": false,
            "show_gift_card_recipient": false,
            "atc_button_background": "",
            "atc_button_text_color": "",
            "payment_button_background": "",
            "payment_button_text_color": ""
          }
        },
        "ff481666-34da-4089-ad31-cb03d9ffc893": {
          "type": "icon_with_text",
          "settings": {
            "image1": "shopify:\/\/shop_images\/mdi_shield-tick.png",
            "icon_size1": 30,
            "title1": "Money Back Guarantee",
            "image2": "shopify:\/\/shop_images\/mdi_truck-delivery.png",
            "icon_size2": 35,
            "title12": "Same Day Shipping"
          }
        },
        "payment_terms": {
          "type": "payment_terms",
          "settings": {
          }
        },
        "separator": {
          "type": "separator",
          "disabled": true,
          "settings": {
          }
        },
        "cd6ba36a-48e1-40f2-a783-9541c8adc725": {
          "type": "product_offer",
          "settings": {
            "text_alignment": "start",
            "icon_position": "aligned",
            "icon": "picto-coupon",
            "custom_icon": "shopify:\/\/shop_images\/TEAM_XND_Logo_100x100px.jpg",
            "icon_width": 72,
            "title": "Become a Member & |Save 25% OFF|",
            "content": "<p>Purchase a Team XND Membership and receive:<\/p><ul><li> 25% Off Sitewide<\/li><li>$100 Worth of Product Rewards  <\/li><li>Free US Shipping.<\/li><li>No Order Minimums.  Exclusive Partner Perks<\/li><\/ul>",
            "product": "team-xnd-membership",
            "background": "#353435",
            "text_color": "#ffffff"
          }
        },
        "description": {
          "type": "description",
          "settings": {
            "collapse_content": true
          }
        },
        "9a72e9ef-1e05-4816-9035-41a075bdf809": {
          "type": "collapsible_text",
          "settings": {
            "title": "Key Benefits",
            "content": "<p>{{ product.metafields.custom.key_benefits | metafield_tag }}<\/p>"
          }
        },
        "b833a344-c331-427c-9113-de7b76a2738c": {
          "type": "collapsible_text",
          "settings": {
            "title": "What's Inside",
            "content": "{{ product.metafields.custom.key_ingredients | metafield_tag }}"
          }
        },
        "ebb6b23d-4582-4ee7-b484-aa7711332c3f": {
          "type": "collapsible_text",
          "settings": {
            "title": "When to Consume",
            "content": "{{ product.metafields.custom.consumption | metafield_tag }}"
          }
        }
      },
      "block_order": [
        "title",
        "e00585ce-7192-4586-9567-a2c4bafdd045",
        "3780c535-8911-4fe4-8d1f-605124beb58c",
        "8d21c681-30df-4742-8a3a-4317b834ba98",
        "variant_picker",
        "607f9e51-9129-4c62-b3f5-158106b03c22",
        "3cbe7afa-04db-4038-8417-654d1167e569",
        "ff481666-34da-4089-ad31-cb03d9ffc893",
        "payment_terms",
        "separator",
        "cd6ba36a-48e1-40f2-a783-9541c8adc725",
        "description",
        "9a72e9ef-1e05-4816-9035-41a075bdf809",
        "b833a344-c331-427c-9113-de7b76a2738c",
        "ebb6b23d-4582-4ee7-b484-aa7711332c3f"
      ],
      "settings": {
        "full_width": true,
        "show_fixed_add_to_cart": true,
        "desktop_media_width": 50,
        "desktop_media_layout": "carousel_thumbnails_left",
        "mobile_media_size": "expanded",
        "mobile_carousel_control": "floating_dots",
        "enable_video_autoplay": false,
        "enable_video_looping": true,
        "enable_image_zoom": false,
        "max_image_zoom_level": 3,
        "background": "",
        "background_gradient": "",
        "text_color": "",
        "input_background": "rgba(0,0,0,0)",
        "input_text_color": ""
      }
    },
    "b5bae039-0209-417a-9002-2d5904e516f8": {
      "type": "accordion-content",
      "blocks": {
        "template--16030540726460__b5bae039-0209-417a-9002-2d5904e516f8-1686818602a6b8ae47-0": {
          "type": "item",
          "settings": {
            "title": "{{ product.metafields.custom.pdp_question_1.value }}",
            "content": "{{ product.metafields.custom.pdp_answer_1 | metafield_tag }}"
          }
        },
        "template--16030540726460__b5bae039-0209-417a-9002-2d5904e516f8-1686818602a6b8ae47-1": {
          "type": "item",
          "settings": {
            "title": "{{ product.metafields.custom.pdp_question_2.value }}",
            "content": "{{ product.metafields.custom.pdp_answer_2 | metafield_tag }}"
          }
        },
        "template--16030540726460__b5bae039-0209-417a-9002-2d5904e516f8-1686818602a6b8ae47-2": {
          "type": "item",
          "settings": {
            "title": "{{ product.metafields.custom.pdp_question_3.value }}",
            "content": "{{ product.metafields.custom.pdp_answer_3 | metafield_tag }}"
          }
        },
        "3a055e44-0985-4287-b5ba-d30a703ed0da": {
          "type": "item",
          "settings": {
            "title": "{{ product.metafields.custom.pdp_question_4.value }}",
            "content": "{{ product.metafields.custom.pdp_answer_4 | metafield_tag }}"
          }
        },
        "2645c719-7e83-405b-b7ae-02ffb2430c11": {
          "type": "item",
          "settings": {
            "title": "{{ product.metafields.custom.pdp_question_5.value }}",
            "content": "{{ product.metafields.custom.pdp_answer_5 | metafield_tag }}"
          }
        },
        "88211187-4dd7-4ab2-b0e2-78f4d5dce849": {
          "type": "item",
          "settings": {
            "title": "{{ product.metafields.custom.pdp_question_6.value }}",
            "content": "{{ product.metafields.custom.pdp_answer_6 | metafield_tag }}"
          }
        },
        "fc772d0c-cea9-4e65-9955-933fd6d64b0f": {
          "type": "item",
          "settings": {
            "title": "{{ product.metafields.custom.pdp_question_7.value }}",
            "content": "{{ product.metafields.custom.pdp_answer_7 | metafield_tag }}"
          }
        }
      },
      "block_order": [
        "template--16030540726460__b5bae039-0209-417a-9002-2d5904e516f8-1686818602a6b8ae47-0",
        "template--16030540726460__b5bae039-0209-417a-9002-2d5904e516f8-1686818602a6b8ae47-1",
        "template--16030540726460__b5bae039-0209-417a-9002-2d5904e516f8-1686818602a6b8ae47-2",
        "3a055e44-0985-4287-b5ba-d30a703ed0da",
        "2645c719-7e83-405b-b7ae-02ffb2430c11",
        "88211187-4dd7-4ab2-b0e2-78f4d5dce849",
        "fc772d0c-cea9-4e65-9955-933fd6d64b0f"
      ],
      "settings": {
        "full_width": true,
        "subheading": "{{ product.metafields.custom.faq_subtitle.value }}",
        "title": "{{ product.metafields.custom.faq_title.value }}",
        "content": "",
        "button_text": "",
        "button_url": "",
        "text_position": "start",
        "background": "",
        "background_gradient": "",
        "text_color": "",
        "heading_color": "",
        "heading_gradient": "",
        "button_background": "",
        "button_text_color": "",
        "accordion_background": "#353435",
        "accordion_text_color": "#ffffff"
      }
    },
    "808ce943-d064-4ee0-9d4c-5381ae09074f": {
      "type": "multi-column",
      "blocks": {
        "template--16030540726460__808ce943-d064-4ee0-9d4c-5381ae09074f-16868199149f11feb4-0": {
          "type": "item",
          "settings": {
            "image": "{{ product.metafields.custom.pdp_athlete_1.value }}",
            "column_size": "3",
            "title": "{{ product.metafields.custom.pdp_athlete_name_1.value }}",
            "heading_tag": "h4",
            "content": "<p><em>{{ product.metafields.custom.pdp_athlete_testimonial_1 | metafield_tag }}<\/em><\/p>",
            "link_url": "",
            "link_text": "",
            "link_style": "link"
          }
        },
        "template--16030540726460__808ce943-d064-4ee0-9d4c-5381ae09074f-16868199149f11feb4-1": {
          "type": "item",
          "settings": {
            "image": "{{ product.metafields.custom.pdp_athlete_2.value }}",
            "column_size": "3",
            "title": "{{ product.metafields.custom.pdp_athlete_name_2.value }}",
            "heading_tag": "h4",
            "content": "{{ product.metafields.custom.pdp_athlete_testimonial_2 | metafield_tag }}",
            "link_url": "",
            "link_text": "",
            "link_style": "link"
          }
        },
        "template--16030540726460__808ce943-d064-4ee0-9d4c-5381ae09074f-16868199149f11feb4-2": {
          "type": "item",
          "settings": {
            "image": "{{ product.metafields.custom.pdp_athlete_3.value }}",
            "column_size": "3",
            "title": "{{ product.metafields.custom.pdp_athlete_name_3.value }}",
            "heading_tag": "h4",
            "content": "{{ product.metafields.custom.pdp_athlete_testimonial_3 | metafield_tag }}",
            "link_url": "",
            "link_text": "",
            "link_style": "link"
          }
        }
      },
      "block_order": [
        "template--16030540726460__808ce943-d064-4ee0-9d4c-5381ae09074f-16868199149f11feb4-0",
        "template--16030540726460__808ce943-d064-4ee0-9d4c-5381ae09074f-16868199149f11feb4-1",
        "template--16030540726460__808ce943-d064-4ee0-9d4c-5381ae09074f-16868199149f11feb4-2"
      ],
      "settings": {
        "full_width": true,
        "stack_on_mobile": false,
        "gap": "medium",
        "text_alignment": "start",
        "subheading": "Proven by Clinical Studies.",
        "title": "Trusted by Clinical Athletes.",
        "content": "<p>Trust is EVERYTHING... That's why Extreme Endurance is used by world-class performers like Josh Bridges to help their chances to get on top of the podium.<\/p>",
        "background": "rgba(0,0,0,0)",
        "background_gradient": "",
        "text_color": "#1a1a1a"
      }
    },
    "related-products": {
      "type": "related-products",
      "settings": {
        "recommendations_count": 6,
        "products": [

        ],
        "full_width": true,
        "stack_products": true,
        "show_progress_bar": false,
        "products_per_row_mobile": "2",
        "products_per_row_desktop": 3,
        "subheading": "",
        "title": "You may also like",
        "content": "",
        "background": "",
        "background_gradient": "",
        "text_color": "",
        "heading_color": "",
        "heading_gradient": "",
        "product_card_background": "",
        "product_card_text_color": ""
      }
    },
    "0a1f82a6-b53d-4501-9a94-2860da5741ce": {
      "type": "media-with-text",
      "blocks": {
        "3e31e3c1-0def-48dd-9655-fe42742306f4": {
          "type": "video",
          "settings": {
            "external_video_url": "https:\/\/www.youtube.com\/watch?v=VKhd6m_axdE&t=59s",
            "poster_image": "shopify:\/\/shop_images\/Screen_Shot_2023-06-06_at_11.06.57_am.png",
            "autoplay": false,
            "media_width": 50,
            "media_position": "start",
            "text_position": "place-self-center-start text-start",
            "icon": "none",
            "icon_width": 48,
            "subheading": "",
            "title": "Join Team XND & Save",
            "content": "<h5>$100 in immediate rewards. Free shipping + 25% off on every order. 2x loyalty points. partner perks.<\/h5>",
            "link_text": "Learn More",
            "link_url": "shopify:\/\/products\/team-xnd-membership",
            "background": "#353435",
            "background_gradient": "",
            "text_color": "#ffffff",
            "text_gradient": "",
            "button_background": "#e93a3f",
            "button_text_color": ""
          }
        }
      },
      "block_order": [
        "3e31e3c1-0def-48dd-9655-fe42742306f4"
      ],
      "settings": {
        "full_width": false,
        "spacing": "small"
      }
    }
  },
  "order": [
    "main",
    "b5bae039-0209-417a-9002-2d5904e516f8",
    "808ce943-d064-4ee0-9d4c-5381ae09074f",
    "related-products",
    "0a1f82a6-b53d-4501-9a94-2860da5741ce"
  ]
}